rma/__init__.py
rma/__pkginfo__.py
rma/application.py
rma/jemalloc.py
rma/redis.py
rma/redis_types.py
rma/scanner.py
rma/splitter.py
rma/cli/__init__.py
rma/cli/rma_cli.py
rma/helpers/__init__.py
rma/helpers/formating.py
rma/helpers/numbers.py
rma/reporters/JsonReporter.py
rma/reporters/TextReporter.py
rma/reporters/__init__.py
rma/rule/GlobalKeySpace.py
rma/rule/Hash.py
rma/rule/KeyString.py
rma/rule/List.py
rma/rule/Set.py
rma/rule/ValueString.py
rma/rule/__init__.py
rma-0.2.1.dist-info/LICENSE
rma-0.2.1.dist-info/METADATA
rma-0.2.1.dist-info/WHEEL
rma-0.2.1.dist-info/entry_points.txt
rma-0.2.1.dist-info/top_level.txt
rma-0.2.1.dist-info/RECORD
