Metadata-Version: 2.1
Name: rma
Version: 0.2.1
Summary: Utilities to profile Redis RAM usage
Home-page: https://github.com/gamenet/redis-memory-analyzer
Author: Nikolay Bondarenko
Author-email: misterionkell@gmail.com
Maintainer: Nikolay Bondarenko
Maintainer-email: misterionkell@gmail.com
License: MIT
Keywords: Redis,Memory Profiler
Platform: UNKNOWN
Classifier: Development Status :: 3 - Alpha
Classifier: Environment :: Console
Classifier: Intended Audience :: Developers
Classifier: License :: OSI Approved :: MIT License
Classifier: Operating System :: OS Independent
Classifier: Programming Language :: Python
Requires-Dist: redis
Requires-Dist: tabulate
Requires-Dist: tqdm
Requires-Dist: msgpack-python
